xarray_beam/__init__.py
xarray_beam/_src/__init__.py
xarray_beam/_src/combiners.py
xarray_beam/_src/combiners_test.py
xarray_beam/_src/core.py
xarray_beam/_src/core_test.py
xarray_beam/_src/dataset.py
xarray_beam/_src/dataset_test.py
xarray_beam/_src/integration_test.py
xarray_beam/_src/range_source.py
xarray_beam/_src/range_source_test.py
xarray_beam/_src/rechunk.py
xarray_beam/_src/rechunk_test.py
xarray_beam/_src/rechunker_algorithm.py
xarray_beam/_src/rechunker_algorithm_test.py
xarray_beam/_src/test_util.py
xarray_beam/_src/threadmap.py
xarray_beam/_src/threadmap_test.py
xarray_beam/_src/zarr.py
xarray_beam/_src/zarr_test.py
xarray_beam-0.11.5.dist-info/licenses/LICENSE
xarray_beam-0.11.5.dist-info/WHEEL
xarray_beam-0.11.5.dist-info/METADATA
xarray_beam-0.11.5.dist-info/RECORD
