Metadata-Version: 2.4
Name: xarray-beam
Version: 0.11.5
Summary: Distributed Xarray with Apache Beam
Author-email: Google LLC <noreply@google.com>
Requires-Python: >=3.10
License-Expression: Apache-2.0
License-File: LICENSE
Requires-Dist: apache_beam>=2.31.0
Requires-Dist: dask
Requires-Dist: fsspec
Requires-Dist: immutabledict
Requires-Dist: zarr
Requires-Dist: xarray
Requires-Dist: myst-nb ; extra == "docs"
Requires-Dist: myst-parser ; extra == "docs"
Requires-Dist: sphinx ; extra == "docs"
Requires-Dist: sphinx_rtd_theme ; extra == "docs"
Requires-Dist: scipy ; extra == "docs"
Requires-Dist: absl-py ; extra == "tests"
Requires-Dist: h5netcdf ; extra == "tests"
Requires-Dist: hypothesis ; extra == "tests"
Requires-Dist: pandas ; extra == "tests"
Requires-Dist: pytest ; extra == "tests"
Requires-Dist: zarr>=3 ; extra == "tests"
Project-URL: documentation, https://xarray-beam.readthedocs.io
Project-URL: source, https://github.com/google/xarray-beam
Provides-Extra: docs
Provides-Extra: tests
